telnetapiconnector/__init__.py
telnetapiconnector/endpoints.py
telnetapiconnector/logger.py
telnetapiconnector/manager.py
telnetapiconnector/models.py
telnetapiconnector-0.1.1.dist-info/METADATA
telnetapiconnector-0.1.1.dist-info/WHEEL
telnetapiconnector-0.1.1.dist-info/top_level.txt
telnetapiconnector-0.1.1.dist-info/RECORD
