Metadata-Version: 2.1
Name: telnetapiconnector
Version: 0.1.1
Summary: A Python library for interacting with the Telnet
Author: Nikita Kudryashov
Author-email: nikitemailua@gmail.com
Classifier: Programming Language :: Python :: 3.10
Classifier: License :: OSI Approved :: MIT License
Classifier: Operating System :: OS Independent
Requires-Python: >=3.10
Requires-Dist: asyncio ~=3.4.3
Requires-Dist: setuptools ~=65.5.0
Requires-Dist: pydantic ~=2.6.4
Requires-Dist: aiohttp ~=3.9.3
